divio_docs_parser/DivioDocs.py
divio_docs_parser/Section.py
divio_docs_parser/__init__.py
divio_docs_parser/constants.py
divio_docs_parser/utils/files.py
divio_docs_parser/utils/markdown_parser.py
divio_docs_parser/utils/regex.py
tests/helpers.py
tests/test_DivioDocs.py
tests/test_Section.py
tests/test_utils_files.py
tests/test_utils_markdown_parser.py
tests/test_utils_regex.py
divio_docs_parser-0.1.2.dist-info/LICENSE
divio_docs_parser-0.1.2.dist-info/METADATA
divio_docs_parser-0.1.2.dist-info/WHEEL
divio_docs_parser-0.1.2.dist-info/top_level.txt
divio_docs_parser-0.1.2.dist-info/RECORD
