Metadata-Version: 2.1
Name: divio_docs_parser
Version: 0.1.2
Summary: Collect and parse all your divio-style documentation with just one line of code!
Author-email: Denperidge <denperidge@gmail.com>
Project-URL: Homepage, https://github.com/Denperidge-Redpencil/divio-docs-parser
Project-URL: Bug Tracker, https://github.com/Denperidge-Redpencil/divio-docs-parser/issues
Classifier: Development Status :: 4 - Beta
Classifier: Intended Audience :: Developers
Classifier: License :: OSI Approved :: MIT License
Classifier: Operating System :: OS Independent
Classifier: Programming Language :: Python :: 3
Classifier: Topic :: Software Development :: Documentation
Classifier: Topic :: Text Processing :: Markup :: Markdown
Requires-Python: >=3.6
License-File: LICENSE
